[{
  "model": "project.task",
  "pk": 4,
  "fields": {
    "creator": 5,
    "last_modifier": 5,
    "date_create": "2021-06-01T13:32:59.111",
    "date_last_modify": "2021-06-16T21:17:36.077",
    "status": 1,
    "ordering": 0,
    "project": 4,
    "name": "Sopralluogo iniziale",
    "assigned_company": 3,
    "shared_task": null,
    "date_start": "2021-06-07",
    "date_end": "2021-06-09",
    "date_completed": null,
    "progress": 78,
    "alert": true,
    "starred": false,
    "note": ""
  }
},
{
  "model": "project.task",
  "pk": 5,
  "fields": {
    "creator": 12,
    "last_modifier": 12,
    "date_create": "2021-06-01T13:33:45.142",
    "date_last_modify": "2021-06-17T12:59:27.618",
    "status": 1,
    "ordering": 0,
    "project": 4,
    "name": "Demolizione interni",
    "assigned_company": 5,
    "shared_task": null,
    "date_start": "2021-06-08",
    "date_end": "2021-06-12",
    "date_completed": null,
    "progress": 0,
    "alert": false,
    "starred": false,
    "note": ""
  }
},
{
  "model": "project.task",
  "pk": 7,
  "fields": {
    "creator": 5,
    "last_modifier": 5,
    "date_create": "2021-06-01T13:34:47.467",
    "date_last_modify": "2021-06-13T12:09:43.438",
    "status": 1,
    "ordering": 0,
    "project": 4,
    "name": "Posa tubi di scarico sanitari",
    "assigned_company": 6,
    "shared_task": null,
    "date_start": "2021-06-14",
    "date_end": "2021-06-18",
    "date_completed": null,
    "progress": 0,
    "alert": true,
    "starred": false,
    "note": ""
  }
},
{
  "model": "project.task",
  "pk": 8,
  "fields": {
    "creator": 5,
    "last_modifier": 5,
    "date_create": "2021-06-01T13:40:48.992",
    "date_last_modify": "2021-06-12T12:16:52.922",
    "status": 1,
    "ordering": 0,
    "project": 4,
    "name": "Installazione putrella e demolizione muro portante",
    "assigned_company": 8,
    "shared_task": null,
    "date_start": "2021-06-16",
    "date_end": "2021-06-18",
    "date_completed": null,
    "progress": 0,
    "alert": false,
    "starred": false,
    "note": ""
  }
},
{
  "model": "project.task",
  "pk": 9,
  "fields": {
    "creator": 5,
    "last_modifier": 5,
    "date_create": "2021-06-01T13:42:24.135",
    "date_last_modify": "2021-06-10T02:26:16.729",
    "status": 1,
    "ordering": 0,
    "project": 4,
    "name": "Collegamenti scarico in fossa biologica",
    "assigned_company": 6,
    "shared_task": null,
    "date_start": "2021-06-21",
    "date_end": "2021-06-23",
    "date_completed": null,
    "progress": 0,
    "alert": false,
    "starred": false,
    "note": ""
  }
},
{
  "model": "project.task",
  "pk": 10,
  "fields": {
    "creator": 5,
    "last_modifier": 5,
    "date_create": "2021-06-01T13:44:22.534",
    "date_last_modify": "2021-06-10T02:26:26.270",
    "status": 1,
    "ordering": 0,
    "project": 4,
    "name": "Installazione scatole di incasso e tubi flessibili",
    "assigned_company": 7,
    "shared_task": null,
    "date_start": "2021-06-22",
    "date_end": "2021-06-25",
    "date_completed": null,
    "progress": 0,
    "alert": false,
    "starred": false,
    "note": ""
  }
},
{
  "model": "project.task",
  "pk": 12,
  "fields": {
    "creator": 5,
    "last_modifier": 5,
    "date_create": "2021-06-01T13:46:22.822",
    "date_last_modify": "2021-06-10T10:34:53.106",
    "status": 1,
    "ordering": 0,
    "project": 4,
    "name": "Sottofondo",
    "assigned_company": 10,
    "shared_task": null,
    "date_start": "2021-06-28",
    "date_end": "2021-07-01",
    "date_completed": null,
    "progress": 0,
    "alert": false,
    "starred": false,
    "note": ""
  }
},
{
  "model": "project.task",
  "pk": 13,
  "fields": {
    "creator": 5,
    "last_modifier": 5,
    "date_create": "2021-06-01T13:47:16.837",
    "date_last_modify": "2021-06-13T13:54:37.767",
    "status": 1,
    "ordering": 0,
    "project": 4,
    "name": "Controsoffitto",
    "assigned_company": 11,
    "shared_task": null,
    "date_start": "2021-07-01",
    "date_end": "2021-07-03",
    "date_completed": null,
    "progress": 0,
    "alert": true,
    "starred": false,
    "note": ""
  }
},
{
  "model": "project.task",
  "pk": 15,
  "fields": {
    "creator": 5,
    "last_modifier": 5,
    "date_create": "2021-06-01T13:51:16.316",
    "date_last_modify": "2021-06-10T02:27:08.686",
    "status": 1,
    "ordering": 0,
    "project": 4,
    "name": "Piastrelle",
    "assigned_company": 9,
    "shared_task": null,
    "date_start": "2021-07-05",
    "date_end": "2021-07-08",
    "date_completed": null,
    "progress": 0,
    "alert": false,
    "starred": false,
    "note": ""
  }
}]